setup.py
django_unique_submission/__init__.py
django_unique_submission/models.py
django_unique_submission.egg-info/PKG-INFO
django_unique_submission.egg-info/SOURCES.txt
django_unique_submission.egg-info/dependency_links.txt
django_unique_submission.egg-info/not-zip-safe
django_unique_submission.egg-info/requires.txt
django_unique_submission.egg-info/top_level.txt