Metadata-Version: 1.1
Name: django-unique-submission
Version: 0.1
Summary: Django unique submission preventing duplicate post data
Home-page: https://github.com/mengzhuo/django-unique-submission
Author: Meng Zhuo
Author-email: mengzhuo1203@gmail.com
License: BSD
Platform: any
Classifier: Environment :: Web Environment
Classifier: Intended Audience :: Developers
Classifier: License :: OSI Approved :: BSD License
Classifier: Operating System :: OS Independent
Classifier: Programming Language :: Python
Classifier: Topic :: Internet :: WWW/HTTP :: Dynamic Content
Classifier: Topic :: Software Development :: Libraries :: Python Modules
